rendercv/__init__.py
rendercv/__main__.py
rendercv/package-lock.json
rendercv/api/__init__.py
rendercv/api/functions.py
rendercv/cli/__init__.py
rendercv/cli/commands.py
rendercv/cli/printer.py
rendercv/cli/utilities.py
rendercv/data/__init__.py
rendercv/data/generator.py
rendercv/data/reader.py
rendercv/data/sample_content.yaml
rendercv/data/models/__init__.py
rendercv/data/models/base.py
rendercv/data/models/computers.py
rendercv/data/models/curriculum_vitae.py
rendercv/data/models/design.py
rendercv/data/models/entry_types.py
rendercv/data/models/locale.py
rendercv/data/models/rendercv_data_model.py
rendercv/data/models/rendercv_settings.py
rendercv/renderer/__init__.py
rendercv/renderer/renderer.py
rendercv/renderer/templater.py
rendercv/themes/__init__.py
rendercv/themes/main.j2.html
rendercv/themes/main.j2.md
rendercv/themes/main.j2.typ
rendercv/themes/options.py
rendercv/themes/classic/BulletEntry.j2.typ
rendercv/themes/classic/EducationEntry.j2.typ
rendercv/themes/classic/ExperienceEntry.j2.typ
rendercv/themes/classic/Header.j2.typ
rendercv/themes/classic/NormalEntry.j2.typ
rendercv/themes/classic/NumberedEntry.j2.typ
rendercv/themes/classic/OneLineEntry.j2.typ
rendercv/themes/classic/Preamble.j2.typ
rendercv/themes/classic/PublicationEntry.j2.typ
rendercv/themes/classic/ReversedNumberedEntry.j2.typ
rendercv/themes/classic/SectionBeginning.j2.typ
rendercv/themes/classic/SectionEnding.j2.typ
rendercv/themes/classic/TextEntry.j2.typ
rendercv/themes/classic/__init__.py
rendercv/themes/components/area.j2.typ
rendercv/themes/components/authors.j2.typ
rendercv/themes/components/company.j2.typ
rendercv/themes/components/date.j2.typ
rendercv/themes/components/degree.j2.typ
rendercv/themes/components/details.j2.typ
rendercv/themes/components/highlights.j2.typ
rendercv/themes/components/institution.j2.typ
rendercv/themes/components/journal.j2.typ
rendercv/themes/components/label.j2.typ
rendercv/themes/components/location.j2.typ
rendercv/themes/components/name.j2.typ
uptal_rendercv-2.4.2.dist-info/METADATA
uptal_rendercv-2.4.2.dist-info/WHEEL
uptal_rendercv-2.4.2.dist-info/entry_points.txt
uptal_rendercv-2.4.2.dist-info/licenses/LICENSE
uptal_rendercv-2.4.2.dist-info/RECORD
