Metadata-Version: 2.4
Name: uptal-rendercv
Version: 2.4.2
Summary: Typst-based CV/resume generator
Project-URL: Web App, https://rendercv.com
Project-URL: Source, https://github.com/rendercv/rendercv
Project-URL: Documentation, https://docs.rendercv.com
Project-URL: Changelog, https://docs.rendercv.com/changelog
Author-email: Sina Atalay <dev@atalay.biz>
License-Expression: MIT
License-File: LICENSE
Classifier: Development Status :: 5 - Production/Stable
Classifier: Intended Audience :: Education
Classifier: Intended Audience :: Science/Research
Classifier: License :: OSI Approved :: MIT License
Classifier: Operating System :: OS Independent
Classifier: Programming Language :: Python :: 3.10
Classifier: Programming Language :: Python :: 3.11
Classifier: Programming Language :: Python :: 3.12
Classifier: Programming Language :: Python :: 3.13
Classifier: Topic :: Printing
Classifier: Topic :: Text Processing :: Markup
Requires-Python: >=3.10
Requires-Dist: email-validator==2.2.0
Requires-Dist: jinja2>=3.1.3
Requires-Dist: pycountry==24.6.1
Requires-Dist: pydantic-extra-types==2.10.2
Requires-Dist: pydantic==2.10.5
Requires-Dist: ruamel-yaml==0.18.6
Provides-Extra: full
Requires-Dist: markdown==3.7; extra == 'full'
Requires-Dist: packaging==24.2; extra == 'full'
Requires-Dist: rendercv-fonts; extra == 'full'
Requires-Dist: typer==0.16.0; extra == 'full'
Requires-Dist: typst==0.13.1; extra == 'full'
Requires-Dist: watchdog==6.0.0; extra == 'full'
